{
  "id" : "testId",
  "hiveConfig": {
    "metaStoreURI": "thrift://sandbox.hortonworks.com:9083",
    "dbName": "default",
    "tblName": "clicks_v2",
    "transactionsPerBatch": 2,
    "batchSize": 10,
    "idlTimeout": 10
  },
  "kafkaConfig": {
    "sourceTopic": "clicks_v2",
    "kafkaSpoutZkHosts": "127.0.0.1",
    "kafkaSpoutZkRoot": "/kafka_storm",
    "kafkaSpoutConsumerClientId": "StormSpoutClientId",
    "kafkaSpoutConsumerGroup": "StormSpoutConsumerGroup",
    "useStartOffsetTimeIfOffsetOutOfRange": true
  },
  "mappingConfig": {
    "fields": [
      {
        "name": "click_key"
      },
      {
        "name": "client_id"
      },
      {
        "name": "ordinal"
      },
      {
        "name": "datetime"
      },
      {
        "name": "user_agent"
      },
      {
        "name": "url"
      },
      {
        "name": "params"
      },
      {
        "name": "tags"
      },
      {
        "name": "dec"
      },
      {
        "name": "json_example"
      },
      {
        "name": "list_example"
      },
      {
        "name": "map_example"
      },
      {
        "name": "struct_example"
      },
      {
        "name": "source_message"
      }
    ],
    "partitionFields": [
      {
        "name": "partition_save_date"
      }
    ]
  },
  "stormConfig": {
    "topologyName": "ClickIngestion",
    "numberOfWorkers": 1,
    "msgTimeoutSeconds": 60,
    "kafkaSpoutCount": 1,
    "mapperBoltCount": 1,
    "hiveBoltCount": 1
  }
}